{"nodes": [{"id": "c_users_idk_desktop_9r5jel1_documents_forgegravity_src_forge_templates_base_py", "label": "base.py", "file_type": "code", "source_file": "src/forge/templates/base.py", "source_location": "L1"}, {"id": "templates_base_template", "label": "Template", "file_type": "code", "source_file": "src/forge/templates/base.py", "source_location": "L8"}, {"id": "abc", "label": "ABC", "file_type": "code", "source_file": "", "source_location": ""}, {"id": "templates_base_template_name", "label": ".name()", "file_type": "code", "source_file": "src/forge/templates/base.py", "source_location": "L17"}, {"id": "templates_base_template_description", "label": ".description()", "file_type": "code", "source_file": "src/forge/templates/base.py", "source_location": "L22"}, {"id": "templates_base_template_default_format", "label": ".default_format()", "file_type": "code", "source_file": "src/forge/templates/base.py", "source_location": "L27"}, {"id": "templates_base_template_seed_topics", "label": ".seed_topics()", "file_type": "code", "source_file": "src/forge/templates/base.py", "source_location": "L31"}, {"id": "templates_base_template_generation_guidelines", "label": ".generation_guidelines()", "file_type": "code", "source_file": "src/forge/templates/base.py", "source_location": "L35"}, {"id": "templates_base_template_estimated_page_count", "label": ".estimated_page_count()", "file_type": "code", "source_file": "src/forge/templates/base.py", "source_location": "L38"}, {"id": "templates_base_template_estimated_sample_count", "label": ".estimated_sample_count()", "file_type": "code", "source_file": "src/forge/templates/base.py", "source_location": "L42"}, {"id": "templates_base_rationale_1", "label": "Template ABC \u2014 domain-specific dataset generation blueprints.", "file_type": "rationale", "source_file": "src/forge/templates/base.py", "source_location": "L1"}, {"id": "templates_base_rationale_9", "label": "Base class for all dataset generation templates.      A template encapsulates do", "file_type": "rationale", "source_file": "src/forge/templates/base.py", "source_location": "L9"}, {"id": "templates_base_rationale_18", "label": "Short identifier (e.g. 'cybersecurity', 'coding').", "file_type": "rationale", "source_file": "src/forge/templates/base.py", "source_location": "L18"}, {"id": "templates_base_rationale_23", "label": "Human-readable description of the template.", "file_type": "rationale", "source_file": "src/forge/templates/base.py", "source_location": "L23"}, {"id": "templates_base_rationale_28", "label": "Default dataset format for this template (e.g. 'reasoning').", "file_type": "rationale", "source_file": "src/forge/templates/base.py", "source_location": "L28"}, {"id": "templates_base_rationale_32", "label": "Initial topics / search queries for the Collect stage.", "file_type": "rationale", "source_file": "src/forge/templates/base.py", "source_location": "L32"}, {"id": "templates_base_rationale_36", "label": "Extra instructions included in generation prompts.", "file_type": "rationale", "source_file": "src/forge/templates/base.py", "source_location": "L36"}, {"id": "templates_base_rationale_39", "label": "Estimated number of web pages to collect.", "file_type": "rationale", "source_file": "src/forge/templates/base.py", "source_location": "L39"}, {"id": "templates_base_rationale_43", "label": "Estimated number of training samples to generate.", "file_type": "rationale", "source_file": "src/forge/templates/base.py", "source_location": "L43"}], "edges": [{"source": "c_users_idk_desktop_9r5jel1_documents_forgegravity_src_forge_templates_base_py", "target": "abc", "relation": "imports_from", "context": "import", "confidence": "EXTRACTED", "source_file": "src/forge/templates/base.py", "source_location": "L5", "weight": 1.0}, {"source": "c_users_idk_desktop_9r5jel1_documents_forgegravity_src_forge_templates_base_py", "target": "templates_base_template", "relation": "contains", "confidence": "EXTRACTED", "source_file": "src/forge/templates/base.py", "source_location": "L8", "weight": 1.0}, {"source": "templates_base_template", "target": "abc", "relation": "inherits", "confidence": "EXTRACTED", "source_file": "src/forge/templates/base.py", "source_location": "L8", "weight": 1.0}, {"source": "templates_base_template", "target": "templates_base_template_name", "relation": "method", "confidence": "EXTRACTED", "source_file": "src/forge/templates/base.py", "source_location": "L17", "weight": 1.0}, {"source": "templates_base_template", "target": "templates_base_template_description", "relation": "method", "confidence": "EXTRACTED", "source_file": "src/forge/templates/base.py", "source_location": "L22", "weight": 1.0}, {"source": "templates_base_template", "target": "templates_base_template_default_format", "relation": "method", "confidence": "EXTRACTED", "source_file": "src/forge/templates/base.py", "source_location": "L27", "weight": 1.0}, {"source": "templates_base_template", "target": "templates_base_template_seed_topics", "relation": "method", "confidence": "EXTRACTED", "source_file": "src/forge/templates/base.py", "source_location": "L31", "weight": 1.0}, {"source": "templates_base_template", "target": "templates_base_template_generation_guidelines", "relation": "method", "confidence": "EXTRACTED", "source_file": "src/forge/templates/base.py", "source_location": "L35", "weight": 1.0}, {"source": "templates_base_template", "target": "templates_base_template_estimated_page_count", "relation": "method", "confidence": "EXTRACTED", "source_file": "src/forge/templates/base.py", "source_location": "L38", "weight": 1.0}, {"source": "templates_base_template", "target": "templates_base_template_estimated_sample_count", "relation": "method", "confidence": "EXTRACTED", "source_file": "src/forge/templates/base.py", "source_location": "L42", "weight": 1.0}, {"source": "templates_base_rationale_1", "target": "c_users_idk_desktop_9r5jel1_documents_forgegravity_src_forge_templates_base_py", "relation": "rationale_for", "confidence": "EXTRACTED", "source_file": "src/forge/templates/base.py", "source_location": "L1", "weight": 1.0}, {"source": "templates_base_rationale_9", "target": "templates_base_template", "relation": "rationale_for", "confidence": "EXTRACTED", "source_file": "src/forge/templates/base.py", "source_location": "L9", "weight": 1.0}, {"source": "templates_base_rationale_18", "target": "templates_base_template_name", "relation": "rationale_for", "confidence": "EXTRACTED", "source_file": "src/forge/templates/base.py", "source_location": "L18", "weight": 1.0}, {"source": "templates_base_rationale_23", "target": "templates_base_template_description", "relation": "rationale_for", "confidence": "EXTRACTED", "source_file": "src/forge/templates/base.py", "source_location": "L23", "weight": 1.0}, {"source": "templates_base_rationale_28", "target": "templates_base_template_default_format", "relation": "rationale_for", "confidence": "EXTRACTED", "source_file": "src/forge/templates/base.py", "source_location": "L28", "weight": 1.0}, {"source": "templates_base_rationale_32", "target": "templates_base_template_seed_topics", "relation": "rationale_for", "confidence": "EXTRACTED", "source_file": "src/forge/templates/base.py", "source_location": "L32", "weight": 1.0}, {"source": "templates_base_rationale_36", "target": "templates_base_template_generation_guidelines", "relation": "rationale_for", "confidence": "EXTRACTED", "source_file": "src/forge/templates/base.py", "source_location": "L36", "weight": 1.0}, {"source": "templates_base_rationale_39", "target": "templates_base_template_estimated_page_count", "relation": "rationale_for", "confidence": "EXTRACTED", "source_file": "src/forge/templates/base.py", "source_location": "L39", "weight": 1.0}, {"source": "templates_base_rationale_43", "target": "templates_base_template_estimated_sample_count", "relation": "rationale_for", "confidence": "EXTRACTED", "source_file": "src/forge/templates/base.py", "source_location": "L43", "weight": 1.0}], "raw_calls": []}